flask_bootstrap_extended/__init__.py
flask_bootstrap_extended/_backwards.py
flask_bootstrap_extended/_compat.py
flask_bootstrap_extended/actions.py
flask_bootstrap_extended/babel.py
flask_bootstrap_extended/base.py
flask_bootstrap_extended/cli.py
flask_bootstrap_extended/consts.py
flask_bootstrap_extended/forms.py
flask_bootstrap_extended/helpers.py
flask_bootstrap_extended/menu.py
flask_bootstrap_extended/module2.py
flask_bootstrap_extended/nav.py
flask_bootstrap_extended/tools.py
flask_bootstrap_extended-5.1.2.dist-info/METADATA
flask_bootstrap_extended-5.1.2.dist-info/WHEEL
flask_bootstrap_extended-5.1.2.dist-info/top_level.txt
flask_bootstrap_extended-5.1.2.dist-info/RECORD
